httpx_cache/__init__.py
httpx_cache/cache_control.py
httpx_cache/client.py
httpx_cache/transport.py
httpx_cache/utils.py
httpx_cache/cache/__init__.py
httpx_cache/cache/base.py
httpx_cache/cache/file.py
httpx_cache/cache/memory.py
httpx_cache/cache/redis.py
httpx_cache/serializer/__init__.py
httpx_cache/serializer/base.py
httpx_cache/serializer/common.py
httpx_cache-0.13.0.dist-info/METADATA
httpx_cache-0.13.0.dist-info/WHEEL
httpx_cache-0.13.0.dist-info/licenses/LICENSE
httpx_cache-0.13.0.dist-info/RECORD
