Metadata-Version: 2.1
Name: httpx-cache
Version: 0.13.0
Summary: Simple caching transport for httpx.
Project-URL: Homepage, https://github.com/obendidi/httpx-cache
Project-URL: Documentation, https://obendidi.github.io/httpx-cache/
Author-email: Ouail Bendidi <ouail.bendidi@gmail.com>
License-File: LICENSE
Keywords: cache,cache-control,httpx
Classifier: Development Status :: 3 - Alpha
Classifier: Environment :: Web Environment
Classifier: Framework :: AsyncIO
Classifier: Intended Audience :: Developers
Classifier: License :: OSI Approved :: BSD License
Classifier: Operating System :: OS Independent
Classifier: Programming Language :: Python :: 3
Classifier: Programming Language :: Python :: 3 :: Only
Classifier: Programming Language :: Python :: 3.7
Classifier: Programming Language :: Python :: 3.8
Classifier: Programming Language :: Python :: 3.9
Classifier: Programming Language :: Python :: 3.10
Classifier: Programming Language :: Python :: 3.11
Classifier: Topic :: Internet :: WWW/HTTP
Classifier: Typing :: Typed
Requires-Python: >=3.8
Requires-Dist: aiorwlock~=1.2
Requires-Dist: anyio~=3.0
Requires-Dist: attrs<24.0,>=21.4
Requires-Dist: fasteners<0.18.0,>=0.16.3
Requires-Dist: httpx<1,>=0.23
Requires-Dist: msgpack~=1.0
Provides-Extra: redis
Requires-Dist: redis~=4.5; extra == 'redis'
